init_data_py/__init__.py
init_data_py/init_data.py
init_data_py/errors/__init__.py
init_data_py/errors/errors.py
init_data_py/types/__init__.py
init_data_py/types/chat.py
init_data_py/types/object.py
init_data_py/types/user.py
init_data_py-0.2.7.dist-info/METADATA
init_data_py-0.2.7.dist-info/WHEEL
init_data_py-0.2.7.dist-info/licenses/LICENCE
init_data_py-0.2.7.dist-info/RECORD
