Metadata-Version: 2.4
Name: init-data-py
Version: 0.2.7
Summary: A Python library that provides tools for using and validating Telegram web app init data.
Author-email: nimaxin <nimaxin@proton.me>
License-Expression: MIT
License-File: LICENCE
Requires-Python: >=3.8
